Metadata-Version: 2.4
Name: orion_py_client
Version: 0.1.14
Summary: Python Client for Orion Feature Store to push/produce Model Features and get features' metadata
Project-URL: Homepage, https://github.com/Meesho/orion/orion_py_client
Project-URL: Bug Tracker, https://github.com/Meesho/orion/issues
Project-URL: Source, https://github.com/meesho/orion/orion_py_client
Author-email: Jaya Kommuru <jaya.kommuru@meesho.com>
License: Apache-2.0
Classifier: License :: OSI Approved :: Apache Software License
Classifier: Operating System :: OS Independent
Classifier: Programming Language :: Python :: 3
Requires-Python: >=3.7
Requires-Dist: cloudpathlib>=0.17.0
Requires-Dist: protobuf>=4.24.1
